votelogger.v
module vote (clock, reset, mode, vv1, vv2, vv3, vv4, count1, count2, count3, count4);

input clock;
input reset;
input mode;
input vv1, vv2, vv3, vv4; //vv = valid vote 

output reg [7:0] count1 , count2, count3 , count4; //8 bit reg to store vote 

always @ (posedge clock)
begin 
if (reset)
begin 
    count1 <= 8'd0;
    count2 <= 8'd0;
    count3 <= 8'd0;
    count4 <= 8'd0;
end 

else 
begin 

if (vv1 && mode == 1'b0)
count1 <= count1 + 1;

else if (vv2 && mode == 1'b0)
count2 <= count2 + 1;

else if (vv3 && mode == 1'b0)
count3 <= count3 + 1;

else if (vv4 && mode == 1'b0)
count4 <= count4 + 1;

end 

end 
endmodule

button.v
module button_control (clock, button, reset, valid);

input clock;
input button;
input reset;

output reg valid;

reg [31:0] counter;

//counter block
always @ (posedge clock)
 begin 
    if (reset)
    counter <= 0;

    else 
    begin 
        if (button && counter < 11)
        counter <= counter + 1;

        else if (!button)
        counter <= 0;
    end
 end 

//valid block
always @ (posedge clock)

begin 
 if (reset) 
 valid <= 1'b0;

 else 
 begin 
    if (counter == 10)
    valid <= 1'b1;
    
    else 
    valid <= 1'b0;
 end

end 

endmodule

main.v
module top (clock, reset, mode, count1, count2, count3, count4, button1, button2, button3, button4);

input clock;
input reset;
input mode;
input button1;
input button2;
input button3;
input button4;
output [7:0] count1;
output [7:0] count2;
output [7:0] count3;
output [7:0] count4;

wire vv1, vv2, vv3, vv4;

button_control bc1 (
        .clock(clock),
        .reset(reset),
        .button(button1),
        .valid (vv1)
);

button_control bc2 (
        .clock(clock),
        .reset(reset),
        .button(button2),
        .valid (vv2)
);

button_control bc3 (
        .clock(clock),
        .reset(reset),
        .button(button3),
        .valid (vv3)
);

button_control bc4 (
        .clock(clock),
        .reset(reset),
        .button(button4),
        .valid (vv4)
);

vote vote_unit (
        .clock(clock),
        .reset(reset),
        .mode(mode),
        .vv1(vv1),
        .vv2(vv2),
        .vv3(vv3),
        .vv4(vv4),
        .count1(count1),
        .count2(count2),
        .count3(count3),
        .count4(count4)
);

//button → button_control → vv → vote → count

endmodule

test.v
`timescale 1ns/1ps

module tb_voting_machine;

reg clock;
reg reset;
reg mode;
reg button1;
reg button2;
reg button3;
reg button4;

wire [7:0] count1;
wire [7:0] count2;
wire [7:0] count3;
wire [7:0] count4;

// Instantiate top module
top dut (
    .clock(clock),
    .reset(reset),
    .mode(mode),
    .button1(button1),
    .button2(button2),
    .button3(button3),
    .button4(button4),
    .count1(count1),
    .count2(count2),
    .count3(count3),
    .count4(count4)
);

// Clock generation
initial begin
    clock = 0;
    forever #5 clock = ~clock;
end

// Stimulus
initial begin
    // Initial values
    reset   = 1;
    mode    = 0;
    button1 = 0;
    button2 = 0;
    button3 = 0;
    button4 = 0;

    // Apply reset
    #20;
    reset = 0;

    // Vote for candidate 1
    $display("Voting for Candidate 1");
    button1 = 1; #100; button1 = 0;
    #20;

    // Vote for candidate 2
    $display("Voting for Candidate 2");
    button2 = 1; #100; button2 = 0;
    #20;

    // Vote for candidate 3
    $display("Voting for Candidate 3");
    button3 = 1; #100; button3 = 0;
    #20;

    // Vote for candidate 4
    $display("Voting for Candidate 4");
    button4 = 1; #100; button4 = 0;
    #20;

    // Switch to result mode
    $display("Switching to RESULT MODE");
    mode = 1;

    // Try voting again (should not count)
    button1 = 1; #100; button1 = 0;
    #20;

    // Final results
    $display("FINAL COUNTS:");
    $display("C1=%0d C2=%0d C3=%0d C4=%0d",
              count1, count2, count3, count4);

    #20;
    $finish;
end

// Waveform dump
initial begin
    $dumpfile("voting_machine.vcd");
    $dumpvars(0, tb_voting_machine);
end

endmodule

voting_machine.vcd
$date
	Thu Jan 22 00:36:06 2026
$end
$version
	Icarus Verilog
$end
$timescale
	1ps
$end
$scope module tb_voting_machine $end
$var wire 8 ! count4 [7:0] $end
$var wire 8 " count3 [7:0] $end
$var wire 8 # count2 [7:0] $end
$var wire 8 $ count1 [7:0] $end
$var reg 1 % button1 $end
$var reg 1 & button2 $end
$var reg 1 ' button3 $end
$var reg 1 ( button4 $end
$var reg 1 ) clock $end
$var reg 1 * mode $end
$var reg 1 + reset $end
$scope module dut $end
$var wire 1 % button1 $end
$var wire 1 & button2 $end
$var wire 1 ' button3 $end
$var wire 1 ( button4 $end
$var wire 1 ) clock $end
$var wire 1 * mode $end
$var wire 1 + reset $end
$var wire 1 , vv4 $end
$var wire 1 - vv3 $end
$var wire 1 . vv2 $end
$var wire 1 / vv1 $end
$var wire 8 0 count4 [7:0] $end
$var wire 8 1 count3 [7:0] $end
$var wire 8 2 count2 [7:0] $end
$var wire 8 3 count1 [7:0] $end
$scope module bc1 $end
$var wire 1 % button $end
$var wire 1 ) clock $end
$var wire 1 + reset $end
$var reg 32 4 counter [31:0] $end
$var reg 1 / valid $end
$upscope $end
$scope module bc2 $end
$var wire 1 & button $end
$var wire 1 ) clock $end
$var wire 1 + reset $end
$var reg 32 5 counter [31:0] $end
$var reg 1 . valid $end
$upscope $end
$scope module bc3 $end
$var wire 1 ' button $end
$var wire 1 ) clock $end
$var wire 1 + reset $end
$var reg 32 6 counter [31:0] $end
$var reg 1 - valid $end
$upscope $end
$scope module bc4 $end
$var wire 1 ( button $end
$var wire 1 ) clock $end
$var wire 1 + reset $end
$var reg 32 7 counter [31:0] $end
$var reg 1 , valid $end
$upscope $end
$scope module vote_unit $end
$var wire 1 ) clock $end
$var wire 1 * mode $end
$var wire 1 + reset $end
$var wire 1 / vv1 $end
$var wire 1 . vv2 $end
$var wire 1 - vv3 $end
$var wire 1 , vv4 $end
$var reg 8 8 count1 [7:0] $end
$var reg 8 9 count2 [7:0] $end
$var reg 8 : count3 [7:0] $end
$var reg 8 ; count4 [7:0] $end
$upscope $end
$upscope $end
$upscope $end
$enddefinitions $end
$comment Show the parameter values. $end
$dumpall
$end
#0
$dumpvars
bx ;
bx :
bx 9
bx 8
bx 7
bx 6
bx 5
bx 4
bx 3
bx 2
bx 1
bx 0
x/
x.
x-
x,
1+
0*
0)
0(
0'
0&
0%
bx $
bx #
bx "
bx !
$end
#5000
b0 4
0/
b0 5
0.
b0 6
0-
b0 7
0,
b0 !
b0 0
b0 ;
b0 "
b0 1
b0 :
b0 #
b0 2
b0 9
b0 $
b0 3
b0 8
1)
#10000
0)
#15000
1)
#20000
0)
1%
0+
#25000
b1 4
1)
#30000
0)
#35000
b10 4
1)
#40000
0)
#45000
b11 4
1)
#50000
0)
#55000
b100 4
1)
#60000
0)
#65000
b101 4
1)
#70000
0)
#75000
b110 4
1)
#80000
0)
#85000
b111 4
1)
#90000
0)
#95000
b1000 4
1)
#100000
0)
#105000
b1001 4
1)
#110000
0)
#115000
b1010 4
1)
#120000
0)
0%
#125000
b0 4
1/
1)
#130000
0)
#135000
b1 $
b1 3
b1 8
0/
1)
#140000
0)
1&
#145000
b1 5
1)
#150000
0)
#155000
b10 5
1)
#160000
0)
#165000
b11 5
1)
#170000
0)
#175000
b100 5
1)
#180000
0)
#185000
b101 5
1)
#190000
0)
#195000
b110 5
1)
#200000
0)
#205000
b111 5
1)
#210000
0)
#215000
b1000 5
1)
#220000
0)
#225000
b1001 5
1)
#230000
0)
#235000
b1010 5
1)
#240000
0)
0&
#245000
b0 5
1.
1)
#250000
0)
#255000
b1 #
b1 2
b1 9
0.
1)
#260000
0)
1'
#265000
b1 6
1)
#270000
0)
#275000
b10 6
1)
#280000
0)
#285000
b11 6
1)
#290000
0)
#295000
b100 6
1)
#300000
0)
#305000
b101 6
1)
#310000
0)
#315000
b110 6
1)
#320000
0)
#325000
b111 6
1)
#330000
0)
#335000
b1000 6
1)
#340000
0)
#345000
b1001 6
1)
#350000
0)
#355000
b1010 6
1)
#360000
0)
0'
#365000
b0 6
1-
1)
#370000
0)
#375000
b1 "
b1 1
b1 :
0-
1)
#380000
0)
1(
#385000
b1 7
1)
#390000
0)
#395000
b10 7
1)
#400000
0)
#405000
b11 7
1)
#410000
0)
#415000
b100 7
1)
#420000
0)
#425000
b101 7
1)
#430000
0)
#435000
b110 7
1)
#440000
0)
#445000
b111 7
1)
#450000
0)
#455000
b1000 7
1)
#460000
0)
#465000
b1001 7
1)
#470000
0)
#475000
b1010 7
1)
#480000
0)
0(
#485000
b0 7
1,
1)
#490000
0)
#495000
b1 !
b1 0
b1 ;
0,
1)
#500000
0)
1%
1*
#505000
b1 4
1)
#510000
0)
#515000
b10 4
1)
#520000
0)
#525000
b11 4
1)
#530000
0)
#535000
b100 4
1)
#540000
0)
#545000
b101 4
1)
#550000
0)
#555000
b110 4
1)
#560000
0)
#565000
b111 4
1)
#570000
0)
#575000
b1000 4
1)
#580000
0)
#585000
b1001 4
1)
#590000
0)
#595000
b1010 4
1)
#600000
0)
0%
#605000
b0 4
1/
1)
#610000
0)
#615000
0/
1)
